llama_index/embeddings/ipex_llm/BUILD
llama_index/embeddings/ipex_llm/__init__.py
llama_index/embeddings/ipex_llm/base.py
llama_index/embeddings/ipex_llm/utils.py
llama_index_embeddings_ipex_llm-0.3.0.dist-info/METADATA
llama_index_embeddings_ipex_llm-0.3.0.dist-info/WHEEL
llama_index_embeddings_ipex_llm-0.3.0.dist-info/RECORD
